[{"Año":2018,"Proyecto - Categoria":"CATEGORÍA B","Estudiante - Genero":"Femenino","Cant_Estudiantes":103,"Porcentaje":21.5},{"Año":2018,"Proyecto - Categoria":"CATEGORÍA B","Estudiante - Genero":"Masculino","Cant_Estudiantes":235,"Porcentaje":49.2},{"Año":2018,"Proyecto - Categoria":"CATEGORÍA B","Estudiante - Genero":"Sin datos","Cant_Estudiantes":140,"Porcentaje":29.3},{"Año":2019,"Proyecto - Categoria":"CATEGORÍA B","Estudiante - Genero":"Femenino","Cant_Estudiantes":306,"Porcentaje":58.5},{"Año":2019,"Proyecto - Categoria":"CATEGORÍA B","Estudiante - Genero":"Masculino","Cant_Estudiantes":216,"Porcentaje":41.3},{"Año":2019,"Proyecto - Categoria":"CATEGORÍA B","Estudiante - Genero":"Sin datos","Cant_Estudiantes":1,"Porcentaje":0.2},{"Año":2021,"Proyecto - Categoria":"CATEGORÍA A","Estudiante - Genero":"Femenino","Cant_Estudiantes":33,"Porcentaje":52.4},{"Año":2021,"Proyecto - Categoria":"CATEGORÍA A","Estudiante - Genero":"Masculino","Cant_Estudiantes":27,"Porcentaje":42.9},{"Año":2021,"Proyecto - Categoria":"CATEGORÍA A","Estudiante - Genero":"Sin datos","Cant_Estudiantes":3,"Porcentaje":4.8},{"Año":2022,"Proyecto - Categoria":"CATEGORÍA A","Estudiante - Genero":"Femenino","Cant_Estudiantes":95,"Porcentaje":56.2},{"Año":2022,"Proyecto - Categoria":"CATEGORÍA A","Estudiante - Genero":"Masculino","Cant_Estudiantes":73,"Porcentaje":43.2},{"Año":2022,"Proyecto - Categoria":"CATEGORÍA A","Estudiante - Genero":"Sin datos","Cant_Estudiantes":1,"Porcentaje":0.6},{"Año":2023,"Proyecto - Categoria":"CATEGORÍA A","Estudiante - Genero":"Femenino","Cant_Estudiantes":218,"Porcentaje":57.2},{"Año":2023,"Proyecto - Categoria":"CATEGORÍA A","Estudiante - Genero":"Masculino","Cant_Estudiantes":163,"Porcentaje":42.8},{"Año":2024,"Proyecto - Categoria":"CATEGORÍA A","Estudiante - Genero":"Femenino","Cant_Estudiantes":79,"Porcentaje":47.0},{"Año":2024,"Proyecto - Categoria":"CATEGORÍA A","Estudiante - Genero":"Masculino","Cant_Estudiantes":89,"Porcentaje":53.0},{"Año":2024,"Proyecto - Categoria":"CATEGORÍA B","Estudiante - Genero":"Femenino","Cant_Estudiantes":74,"Porcentaje":48.1},{"Año":2024,"Proyecto - Categoria":"CATEGORÍA B","Estudiante - Genero":"Masculino","Cant_Estudiantes":80,"Porcentaje":51.9},{"Año":2024,"Proyecto - Categoria":"CATEGORÍA C","Estudiante - Genero":"Femenino","Cant_Estudiantes":121,"Porcentaje":57.3},{"Año":2024,"Proyecto - Categoria":"CATEGORÍA C","Estudiante - Genero":"Masculino","Cant_Estudiantes":90,"Porcentaje":42.7},{"Año":2025,"Proyecto - Categoria":"CATEGORÍA A","Estudiante - Genero":"Femenino","Cant_Estudiantes":99,"Porcentaje":50.5},{"Año":2025,"Proyecto - Categoria":"CATEGORÍA A","Estudiante - Genero":"Masculino","Cant_Estudiantes":97,"Porcentaje":49.5},{"Año":2025,"Proyecto - Categoria":"CATEGORÍA B","Estudiante - Genero":"Femenino","Cant_Estudiantes":122,"Porcentaje":54.2},{"Año":2025,"Proyecto - Categoria":"CATEGORÍA B","Estudiante - Genero":"Masculino","Cant_Estudiantes":103,"Porcentaje":45.8},{"Año":2025,"Proyecto - Categoria":"CATEGORÍA C","Estudiante - Genero":"Femenino","Cant_Estudiantes":146,"Porcentaje":56.2},{"Año":2025,"Proyecto - Categoria":"CATEGORÍA C","Estudiante - Genero":"Masculino","Cant_Estudiantes":114,"Porcentaje":43.8}]