[{"Tema":"bondades matico","Frecuencia":1,"Año":2021},{"Tema":"juegos naves","Frecuencia":1,"Año":2021},{"Tema":"juegos naves pandemia","Frecuencia":1,"Año":2021},{"Tema":"naves pandemia","Frecuencia":1,"Año":2021},{"Tema":"barredor basura","Frecuencia":1,"Año":2022},{"Tema":"barredor basura recogedor","Frecuencia":1,"Año":2022},{"Tema":"basura recogedor","Frecuencia":1,"Año":2022},{"Tema":"basura recogedor objetos","Frecuencia":1,"Año":2022},{"Tema":"caseras enfermedades","Frecuencia":1,"Año":2022},{"Tema":"abejas aguijon","Frecuencia":1,"Año":2025},{"Tema":"abejas aguijon bosque","Frecuencia":1,"Año":2025},{"Tema":"agua vida","Frecuencia":1,"Año":2025},{"Tema":"agua vida jabon","Frecuencia":1,"Año":2025},{"Tema":"aguijon bosque","Frecuencia":1,"Año":2025}]