[{"Año":2018,"Estudiante - Grado":"CUARTO","Estudiante - Genero":"Femenino","Cant_Estudiantes":18,"Porcentaje":18.8},{"Año":2018,"Estudiante - Grado":"CUARTO","Estudiante - Genero":"Masculino","Cant_Estudiantes":35,"Porcentaje":36.5},{"Año":2018,"Estudiante - Grado":"CUARTO","Estudiante - Genero":"Sin datos","Cant_Estudiantes":43,"Porcentaje":44.8},{"Año":2018,"Estudiante - Grado":"PRIMERO","Estudiante - Genero":"Femenino","Cant_Estudiantes":5,"Porcentaje":19.2},{"Año":2018,"Estudiante - Grado":"PRIMERO","Estudiante - Genero":"Masculino","Cant_Estudiantes":13,"Porcentaje":50.0},{"Año":2018,"Estudiante - Grado":"PRIMERO","Estudiante - Genero":"Sin datos","Cant_Estudiantes":8,"Porcentaje":30.8},{"Año":2018,"Estudiante - Grado":"QUINTO","Estudiante - Genero":"Femenino","Cant_Estudiantes":1,"Porcentaje":0.9},{"Año":2018,"Estudiante - Grado":"QUINTO","Estudiante - Genero":"Masculino","Cant_Estudiantes":44,"Porcentaje":40.7},{"Año":2018,"Estudiante - Grado":"QUINTO","Estudiante - Genero":"Sin datos","Cant_Estudiantes":63,"Porcentaje":58.3},{"Año":2018,"Estudiante - Grado":"SEGUNDO","Estudiante - Genero":"Femenino","Cant_Estudiantes":4,"Porcentaje":13.8},{"Año":2018,"Estudiante - Grado":"SEGUNDO","Estudiante - Genero":"Masculino","Cant_Estudiantes":15,"Porcentaje":51.7},{"Año":2018,"Estudiante - Grado":"SEGUNDO","Estudiante - Genero":"Sin datos","Cant_Estudiantes":10,"Porcentaje":34.5},{"Año":2018,"Estudiante - Grado":"TERCERO","Estudiante - Genero":"Femenino","Cant_Estudiantes":16,"Porcentaje":20.5},{"Año":2018,"Estudiante - Grado":"TERCERO","Estudiante - Genero":"Masculino","Cant_Estudiantes":36,"Porcentaje":46.2},{"Año":2018,"Estudiante - Grado":"TERCERO","Estudiante - Genero":"Sin datos","Cant_Estudiantes":26,"Porcentaje":33.3},{"Año":2019,"Estudiante - Grado":"CUARTO","Estudiante - Genero":"Femenino","Cant_Estudiantes":90,"Porcentaje":57.7},{"Año":2019,"Estudiante - Grado":"CUARTO","Estudiante - Genero":"Masculino","Cant_Estudiantes":66,"Porcentaje":42.3},{"Año":2019,"Estudiante - Grado":"PRIMERO","Estudiante - Genero":"Femenino","Cant_Estudiantes":40,"Porcentaje":65.6},{"Año":2019,"Estudiante - Grado":"PRIMERO","Estudiante - Genero":"Masculino","Cant_Estudiantes":21,"Porcentaje":34.4},{"Año":2019,"Estudiante - Grado":"QUINTO","Estudiante - Genero":"Femenino","Cant_Estudiantes":62,"Porcentaje":49.6},{"Año":2019,"Estudiante - Grado":"QUINTO","Estudiante - Genero":"Masculino","Cant_Estudiantes":63,"Porcentaje":50.4},{"Año":2019,"Estudiante - Grado":"SEGUNDO","Estudiante - Genero":"Femenino","Cant_Estudiantes":38,"Porcentaje":60.3},{"Año":2019,"Estudiante - Grado":"SEGUNDO","Estudiante - Genero":"Masculino","Cant_Estudiantes":25,"Porcentaje":39.7},{"Año":2019,"Estudiante - Grado":"TERCERO","Estudiante - Genero":"Femenino","Cant_Estudiantes":57,"Porcentaje":64.0},{"Año":2019,"Estudiante - Grado":"TERCERO","Estudiante - Genero":"Masculino","Cant_Estudiantes":32,"Porcentaje":36.0},{"Año":2020,"Estudiante - Grado":"CUARTO","Estudiante - Genero":"Femenino","Cant_Estudiantes":11,"Porcentaje":50.0},{"Año":2020,"Estudiante - Grado":"CUARTO","Estudiante - Genero":"Masculino","Cant_Estudiantes":11,"Porcentaje":50.0},{"Año":2020,"Estudiante - Grado":"PRIMERO","Estudiante - Genero":"Femenino","Cant_Estudiantes":7,"Porcentaje":53.8},{"Año":2020,"Estudiante - Grado":"PRIMERO","Estudiante - Genero":"Masculino","Cant_Estudiantes":6,"Porcentaje":46.2},{"Año":2020,"Estudiante - Grado":"QUINTO","Estudiante - Genero":"Femenino","Cant_Estudiantes":19,"Porcentaje":61.3},{"Año":2020,"Estudiante - Grado":"QUINTO","Estudiante - Genero":"Masculino","Cant_Estudiantes":12,"Porcentaje":38.7},{"Año":2020,"Estudiante - Grado":"SEGUNDO","Estudiante - Genero":"Femenino","Cant_Estudiantes":11,"Porcentaje":55.0},{"Año":2020,"Estudiante - Grado":"SEGUNDO","Estudiante - Genero":"Masculino","Cant_Estudiantes":9,"Porcentaje":45.0},{"Año":2020,"Estudiante - Grado":"TERCERO","Estudiante - Genero":"Femenino","Cant_Estudiantes":11,"Porcentaje":73.3},{"Año":2020,"Estudiante - Grado":"TERCERO","Estudiante - Genero":"Masculino","Cant_Estudiantes":4,"Porcentaje":26.7},{"Año":2021,"Estudiante - Grado":"CUARTO","Estudiante - Genero":"Femenino","Cant_Estudiantes":33,"Porcentaje":73.3},{"Año":2021,"Estudiante - Grado":"CUARTO","Estudiante - Genero":"Masculino","Cant_Estudiantes":11,"Porcentaje":24.4},{"Año":2021,"Estudiante - Grado":"CUARTO","Estudiante - Genero":"Sin datos","Cant_Estudiantes":1,"Porcentaje":2.2},{"Año":2021,"Estudiante - Grado":"PRIMERO","Estudiante - Genero":"Femenino","Cant_Estudiantes":17,"Porcentaje":60.7},{"Año":2021,"Estudiante - Grado":"PRIMERO","Estudiante - Genero":"Masculino","Cant_Estudiantes":11,"Porcentaje":39.3},{"Año":2021,"Estudiante - Grado":"QUINTO","Estudiante - Genero":"Femenino","Cant_Estudiantes":31,"Porcentaje":53.4},{"Año":2021,"Estudiante - Grado":"QUINTO","Estudiante - Genero":"Masculino","Cant_Estudiantes":27,"Porcentaje":46.6},{"Año":2021,"Estudiante - Grado":"SEGUNDO","Estudiante - Genero":"Femenino","Cant_Estudiantes":27,"Porcentaje":77.1},{"Año":2021,"Estudiante - Grado":"SEGUNDO","Estudiante - Genero":"Masculino","Cant_Estudiantes":8,"Porcentaje":22.9},{"Año":2021,"Estudiante - Grado":"TERCERO","Estudiante - Genero":"Femenino","Cant_Estudiantes":27,"Porcentaje":57.4},{"Año":2021,"Estudiante - Grado":"TERCERO","Estudiante - Genero":"Masculino","Cant_Estudiantes":20,"Porcentaje":42.6},{"Año":2022,"Estudiante - Grado":"CUARTO","Estudiante - Genero":"Femenino","Cant_Estudiantes":46,"Porcentaje":63.0},{"Año":2022,"Estudiante - Grado":"CUARTO","Estudiante - Genero":"Masculino","Cant_Estudiantes":27,"Porcentaje":37.0},{"Año":2022,"Estudiante - Grado":"PRIMERO","Estudiante - Genero":"Femenino","Cant_Estudiantes":17,"Porcentaje":63.0},{"Año":2022,"Estudiante - Grado":"PRIMERO","Estudiante - Genero":"Masculino","Cant_Estudiantes":10,"Porcentaje":37.0},{"Año":2022,"Estudiante - Grado":"QUINTO","Estudiante - Genero":"Femenino","Cant_Estudiantes":61,"Porcentaje":64.9},{"Año":2022,"Estudiante - Grado":"QUINTO","Estudiante - Genero":"Masculino","Cant_Estudiantes":33,"Porcentaje":35.1},{"Año":2022,"Estudiante - Grado":"SEGUNDO","Estudiante - Genero":"Femenino","Cant_Estudiantes":31,"Porcentaje":64.6},{"Año":2022,"Estudiante - Grado":"SEGUNDO","Estudiante - Genero":"Masculino","Cant_Estudiantes":17,"Porcentaje":35.4},{"Año":2022,"Estudiante - Grado":"TERCERO","Estudiante - Genero":"Femenino","Cant_Estudiantes":36,"Porcentaje":57.1},{"Año":2022,"Estudiante - Grado":"TERCERO","Estudiante - Genero":"Masculino","Cant_Estudiantes":27,"Porcentaje":42.9},{"Año":2023,"Estudiante - Grado":"CUARTO","Estudiante - Genero":"Femenino","Cant_Estudiantes":76,"Porcentaje":66.7},{"Año":2023,"Estudiante - Grado":"CUARTO","Estudiante - Genero":"Masculino","Cant_Estudiantes":38,"Porcentaje":33.3},{"Año":2023,"Estudiante - Grado":"PRIMERO","Estudiante - Genero":"Femenino","Cant_Estudiantes":37,"Porcentaje":56.9},{"Año":2023,"Estudiante - Grado":"PRIMERO","Estudiante - Genero":"Masculino","Cant_Estudiantes":28,"Porcentaje":43.1},{"Año":2023,"Estudiante - Grado":"QUINTO","Estudiante - Genero":"Femenino","Cant_Estudiantes":78,"Porcentaje":63.9},{"Año":2023,"Estudiante - Grado":"QUINTO","Estudiante - Genero":"Masculino","Cant_Estudiantes":44,"Porcentaje":36.1},{"Año":2023,"Estudiante - Grado":"SEGUNDO","Estudiante - Genero":"Femenino","Cant_Estudiantes":42,"Porcentaje":61.8},{"Año":2023,"Estudiante - Grado":"SEGUNDO","Estudiante - Genero":"Masculino","Cant_Estudiantes":26,"Porcentaje":38.2},{"Año":2023,"Estudiante - Grado":"TERCERO","Estudiante - Genero":"Femenino","Cant_Estudiantes":57,"Porcentaje":68.7},{"Año":2023,"Estudiante - Grado":"TERCERO","Estudiante - Genero":"Masculino","Cant_Estudiantes":26,"Porcentaje":31.3},{"Año":2024,"Estudiante - Grado":"CUARTO","Estudiante - Genero":"Femenino","Cant_Estudiantes":75,"Porcentaje":63.6},{"Año":2024,"Estudiante - Grado":"CUARTO","Estudiante - Genero":"Masculino","Cant_Estudiantes":43,"Porcentaje":36.4},{"Año":2024,"Estudiante - Grado":"PRIMERO","Estudiante - Genero":"Femenino","Cant_Estudiantes":39,"Porcentaje":55.7},{"Año":2024,"Estudiante - Grado":"PRIMERO","Estudiante - Genero":"Masculino","Cant_Estudiantes":31,"Porcentaje":44.3},{"Año":2024,"Estudiante - Grado":"QUINTO","Estudiante - Genero":"Femenino","Cant_Estudiantes":80,"Porcentaje":61.1},{"Año":2024,"Estudiante - Grado":"QUINTO","Estudiante - Genero":"Masculino","Cant_Estudiantes":51,"Porcentaje":38.9},{"Año":2024,"Estudiante - Grado":"SEGUNDO","Estudiante - Genero":"Femenino","Cant_Estudiantes":89,"Porcentaje":58.2},{"Año":2024,"Estudiante - Grado":"SEGUNDO","Estudiante - Genero":"Masculino","Cant_Estudiantes":64,"Porcentaje":41.8},{"Año":2024,"Estudiante - Grado":"TERCERO","Estudiante - Genero":"Femenino","Cant_Estudiantes":73,"Porcentaje":70.2},{"Año":2024,"Estudiante - Grado":"TERCERO","Estudiante - Genero":"Masculino","Cant_Estudiantes":31,"Porcentaje":29.8},{"Año":2025,"Estudiante - Grado":"CUARTO","Estudiante - Genero":"Femenino","Cant_Estudiantes":89,"Porcentaje":59.7},{"Año":2025,"Estudiante - Grado":"CUARTO","Estudiante - Genero":"Masculino","Cant_Estudiantes":60,"Porcentaje":40.3},{"Año":2025,"Estudiante - Grado":"PRIMERO","Estudiante - Genero":"Femenino","Cant_Estudiantes":58,"Porcentaje":58.0},{"Año":2025,"Estudiante - Grado":"PRIMERO","Estudiante - Genero":"Masculino","Cant_Estudiantes":42,"Porcentaje":42.0},{"Año":2025,"Estudiante - Grado":"QUINTO","Estudiante - Genero":"Femenino","Cant_Estudiantes":98,"Porcentaje":71.0},{"Año":2025,"Estudiante - Grado":"QUINTO","Estudiante - Genero":"Masculino","Cant_Estudiantes":40,"Porcentaje":29.0},{"Año":2025,"Estudiante - Grado":"SEGUNDO","Estudiante - Genero":"Femenino","Cant_Estudiantes":88,"Porcentaje":61.5},{"Año":2025,"Estudiante - Grado":"SEGUNDO","Estudiante - Genero":"Masculino","Cant_Estudiantes":55,"Porcentaje":38.5},{"Año":2025,"Estudiante - Grado":"TERCERO","Estudiante - Genero":"Femenino","Cant_Estudiantes":48,"Porcentaje":57.8},{"Año":2025,"Estudiante - Grado":"TERCERO","Estudiante - Genero":"Masculino","Cant_Estudiantes":35,"Porcentaje":42.2}]