[{"Año":2018,"Proyecto - Categoria":"CATEGORÍA C","Proyecto - Area":"CIENCIAS AMBIENTALES","Estudiante - Genero":"Femenino","Cant_Estudiantes":16,"Porcentaje":15.0},{"Año":2018,"Proyecto - Categoria":"CATEGORÍA C","Proyecto - Area":"CIENCIAS AMBIENTALES","Estudiante - Genero":"Masculino","Cant_Estudiantes":42,"Porcentaje":39.3},{"Año":2018,"Proyecto - Categoria":"CATEGORÍA C","Proyecto - Area":"CIENCIAS AMBIENTALES","Estudiante - Genero":"Sin datos","Cant_Estudiantes":49,"Porcentaje":45.8},{"Año":2018,"Proyecto - Categoria":"CATEGORÍA C","Proyecto - Area":"CIENCIAS BÁSICAS","Estudiante - Genero":"Femenino","Cant_Estudiantes":15,"Porcentaje":16.3},{"Año":2018,"Proyecto - Categoria":"CATEGORÍA C","Proyecto - Area":"CIENCIAS BÁSICAS","Estudiante - Genero":"Masculino","Cant_Estudiantes":45,"Porcentaje":48.9},{"Año":2018,"Proyecto - Categoria":"CATEGORÍA C","Proyecto - Area":"CIENCIAS BÁSICAS","Estudiante - Genero":"Sin datos","Cant_Estudiantes":32,"Porcentaje":34.8},{"Año":2018,"Proyecto - Categoria":"CATEGORÍA C","Proyecto - Area":"TECNOLOGÍA E INGENIERÍA","Estudiante - Genero":"Femenino","Cant_Estudiantes":10,"Porcentaje":9.8},{"Año":2018,"Proyecto - Categoria":"CATEGORÍA C","Proyecto - Area":"TECNOLOGÍA E INGENIERÍA","Estudiante - Genero":"Masculino","Cant_Estudiantes":49,"Porcentaje":48.0},{"Año":2018,"Proyecto - Categoria":"CATEGORÍA C","Proyecto - Area":"TECNOLOGÍA E INGENIERÍA","Estudiante - Genero":"Sin datos","Cant_Estudiantes":43,"Porcentaje":42.2},{"Año":2018,"Proyecto - Categoria":"CATEGORÍA D","Proyecto - Area":"CIENCIAS SOCIALES Y CIUDADANÍA","Estudiante - Genero":"Femenino","Cant_Estudiantes":3,"Porcentaje":8.3},{"Año":2018,"Proyecto - Categoria":"CATEGORÍA D","Proyecto - Area":"CIENCIAS SOCIALES Y CIUDADANÍA","Estudiante - Genero":"Masculino","Cant_Estudiantes":7,"Porcentaje":19.4},{"Año":2018,"Proyecto - Categoria":"CATEGORÍA D","Proyecto - Area":"CIENCIAS SOCIALES Y CIUDADANÍA","Estudiante - Genero":"Sin datos","Cant_Estudiantes":26,"Porcentaje":72.2},{"Año":2019,"Proyecto - Categoria":"CATEGORÍA C","Proyecto - Area":"CIENCIAS AMBIENTALES","Estudiante - Genero":"Femenino","Cant_Estudiantes":88,"Porcentaje":59.1},{"Año":2019,"Proyecto - Categoria":"CATEGORÍA C","Proyecto - Area":"CIENCIAS AMBIENTALES","Estudiante - Genero":"Masculino","Cant_Estudiantes":61,"Porcentaje":40.9},{"Año":2019,"Proyecto - Categoria":"CATEGORÍA C","Proyecto - Area":"CIENCIAS BÁSICAS","Estudiante - Genero":"Femenino","Cant_Estudiantes":78,"Porcentaje":60.9},{"Año":2019,"Proyecto - Categoria":"CATEGORÍA C","Proyecto - Area":"CIENCIAS BÁSICAS","Estudiante - Genero":"Masculino","Cant_Estudiantes":50,"Porcentaje":39.1},{"Año":2019,"Proyecto - Categoria":"CATEGORÍA C","Proyecto - Area":"TECNOLOGÍA E INGENIERÍA","Estudiante - Genero":"Femenino","Cant_Estudiantes":84,"Porcentaje":50.3},{"Año":2019,"Proyecto - Categoria":"CATEGORÍA C","Proyecto - Area":"TECNOLOGÍA E INGENIERÍA","Estudiante - Genero":"Masculino","Cant_Estudiantes":83,"Porcentaje":49.7},{"Año":2019,"Proyecto - Categoria":"CATEGORÍA D","Proyecto - Area":"CIENCIAS SOCIALES Y CIUDADANÍA","Estudiante - Genero":"Femenino","Cant_Estudiantes":37,"Porcentaje":74.0},{"Año":2019,"Proyecto - Categoria":"CATEGORÍA D","Proyecto - Area":"CIENCIAS SOCIALES Y CIUDADANÍA","Estudiante - Genero":"Masculino","Cant_Estudiantes":13,"Porcentaje":26.0},{"Año":2020,"Proyecto - Categoria":"UNICA","Proyecto - Area":"Área de Alternativa de Solución Tecnológica","Estudiante - Genero":"Femenino","Cant_Estudiantes":25,"Porcentaje":55.6},{"Año":2020,"Proyecto - Categoria":"UNICA","Proyecto - Area":"Área de Alternativa de Solución Tecnológica","Estudiante - Genero":"Masculino","Cant_Estudiantes":20,"Porcentaje":44.4},{"Año":2020,"Proyecto - Categoria":"UNICA","Proyecto - Area":"Área de Indagación Científica","Estudiante - Genero":"Femenino","Cant_Estudiantes":25,"Porcentaje":59.5},{"Año":2020,"Proyecto - Categoria":"UNICA","Proyecto - Area":"Área de Indagación Científica","Estudiante - Genero":"Masculino","Cant_Estudiantes":17,"Porcentaje":40.5},{"Año":2020,"Proyecto - Categoria":"UNICA","Proyecto - Area":"Área de Indagación Cualitativa","Estudiante - Genero":"Femenino","Cant_Estudiantes":9,"Porcentaje":64.3},{"Año":2020,"Proyecto - Categoria":"UNICA","Proyecto - Area":"Área de Indagación Cualitativa","Estudiante - Genero":"Masculino","Cant_Estudiantes":5,"Porcentaje":35.7},{"Año":2021,"Proyecto - Categoria":"CATEGORÍA B","Proyecto - Area":"ALTERNATIVA DE SOLUCION TECNOLOGICA","Estudiante - Genero":"Femenino","Cant_Estudiantes":50,"Porcentaje":53.8},{"Año":2021,"Proyecto - Categoria":"CATEGORÍA B","Proyecto - Area":"ALTERNATIVA DE SOLUCION TECNOLOGICA","Estudiante - Genero":"Masculino","Cant_Estudiantes":42,"Porcentaje":45.2},{"Año":2021,"Proyecto - Categoria":"CATEGORÍA B","Proyecto - Area":"ALTERNATIVA DE SOLUCION TECNOLOGICA","Estudiante - Genero":"Sin datos","Cant_Estudiantes":1,"Porcentaje":1.1},{"Año":2021,"Proyecto - Categoria":"CATEGORÍA B","Proyecto - Area":"INDAGACION CIENTIFICA","Estudiante - Genero":"Femenino","Cant_Estudiantes":61,"Porcentaje":66.3},{"Año":2021,"Proyecto - Categoria":"CATEGORÍA B","Proyecto - Area":"INDAGACION CIENTIFICA","Estudiante - Genero":"Masculino","Cant_Estudiantes":31,"Porcentaje":33.7},{"Año":2021,"Proyecto - Categoria":"CATEGORÍA B","Proyecto - Area":"INDAGACION CUALITATIVA","Estudiante - Genero":"Femenino","Cant_Estudiantes":25,"Porcentaje":86.2},{"Año":2021,"Proyecto - Categoria":"CATEGORÍA B","Proyecto - Area":"INDAGACION CUALITATIVA","Estudiante - Genero":"Masculino","Cant_Estudiantes":4,"Porcentaje":13.8},{"Año":2022,"Proyecto - Categoria":"CATEGORÍA B","Proyecto - Area":"ALTERNATIVA DE SOLUCION TECNOLOGICA","Estudiante - Genero":"Femenino","Cant_Estudiantes":97,"Porcentaje":59.1},{"Año":2022,"Proyecto - Categoria":"CATEGORÍA B","Proyecto - Area":"ALTERNATIVA DE SOLUCION TECNOLOGICA","Estudiante - Genero":"Masculino","Cant_Estudiantes":67,"Porcentaje":40.9},{"Año":2022,"Proyecto - Categoria":"CATEGORÍA B","Proyecto - Area":"INDAGACION CIENTIFICA","Estudiante - Genero":"Femenino","Cant_Estudiantes":71,"Porcentaje":63.4},{"Año":2022,"Proyecto - Categoria":"CATEGORÍA B","Proyecto - Area":"INDAGACION CIENTIFICA","Estudiante - Genero":"Masculino","Cant_Estudiantes":41,"Porcentaje":36.6},{"Año":2022,"Proyecto - Categoria":"CATEGORÍA B","Proyecto - Area":"INDAGACION CUALITATIVA","Estudiante - Genero":"Femenino","Cant_Estudiantes":23,"Porcentaje":79.3},{"Año":2022,"Proyecto - Categoria":"CATEGORÍA B","Proyecto - Area":"INDAGACION CUALITATIVA","Estudiante - Genero":"Masculino","Cant_Estudiantes":6,"Porcentaje":20.7},{"Año":2023,"Proyecto - Categoria":"CATEGORÍA B","Proyecto - Area":"ALTERNATIVA DE SOLUCIÓN TECNOLÓGICA","Estudiante - Genero":"Femenino","Cant_Estudiantes":134,"Porcentaje":61.5},{"Año":2023,"Proyecto - Categoria":"CATEGORÍA B","Proyecto - Area":"ALTERNATIVA DE SOLUCIÓN TECNOLÓGICA","Estudiante - Genero":"Masculino","Cant_Estudiantes":84,"Porcentaje":38.5},{"Año":2023,"Proyecto - Categoria":"CATEGORÍA B","Proyecto - Area":"INDAGACIÓN CIENTÍFICA","Estudiante - Genero":"Femenino","Cant_Estudiantes":110,"Porcentaje":64.0},{"Año":2023,"Proyecto - Categoria":"CATEGORÍA B","Proyecto - Area":"INDAGACIÓN CIENTÍFICA","Estudiante - Genero":"Masculino","Cant_Estudiantes":62,"Porcentaje":36.0},{"Año":2023,"Proyecto - Categoria":"CATEGORÍA B","Proyecto - Area":"INDAGACIÓN CUALITATIVA","Estudiante - Genero":"Femenino","Cant_Estudiantes":46,"Porcentaje":74.2},{"Año":2023,"Proyecto - Categoria":"CATEGORÍA B","Proyecto - Area":"INDAGACIÓN CUALITATIVA","Estudiante - Genero":"Masculino","Cant_Estudiantes":16,"Porcentaje":25.8},{"Año":2024,"Proyecto - Categoria":"CATEGORÍA D","Proyecto - Area":"CIENCIA Y TECNOLOGÍA","Estudiante - Genero":"Femenino","Cant_Estudiantes":119,"Porcentaje":56.1},{"Año":2024,"Proyecto - Categoria":"CATEGORÍA D","Proyecto - Area":"CIENCIA Y TECNOLOGÍA","Estudiante - Genero":"Masculino","Cant_Estudiantes":93,"Porcentaje":43.9},{"Año":2024,"Proyecto - Categoria":"CATEGORÍA D","Proyecto - Area":"CIENCIAS SOCIALES","Estudiante - Genero":"Femenino","Cant_Estudiantes":9,"Porcentaje":81.8},{"Año":2024,"Proyecto - Categoria":"CATEGORÍA D","Proyecto - Area":"CIENCIAS SOCIALES","Estudiante - Genero":"Masculino","Cant_Estudiantes":2,"Porcentaje":18.2},{"Año":2024,"Proyecto - Categoria":"CATEGORÍA E","Proyecto - Area":"CIENCIA Y TECNOLOGÍA","Estudiante - Genero":"Femenino","Cant_Estudiantes":200,"Porcentaje":62.7},{"Año":2024,"Proyecto - Categoria":"CATEGORÍA E","Proyecto - Area":"CIENCIA Y TECNOLOGÍA","Estudiante - Genero":"Masculino","Cant_Estudiantes":119,"Porcentaje":37.3},{"Año":2024,"Proyecto - Categoria":"CATEGORÍA E","Proyecto - Area":"CIENCIAS SOCIALES","Estudiante - Genero":"Femenino","Cant_Estudiantes":28,"Porcentaje":82.4},{"Año":2024,"Proyecto - Categoria":"CATEGORÍA E","Proyecto - Area":"CIENCIAS SOCIALES","Estudiante - Genero":"Masculino","Cant_Estudiantes":6,"Porcentaje":17.6},{"Año":2025,"Proyecto - Categoria":"CATEGORÍA D","Proyecto - Area":"Ciencias Sociales","Estudiante - Genero":"Femenino","Cant_Estudiantes":13,"Porcentaje":54.2},{"Año":2025,"Proyecto - Categoria":"CATEGORÍA D","Proyecto - Area":"Ciencias Sociales","Estudiante - Genero":"Masculino","Cant_Estudiantes":11,"Porcentaje":45.8},{"Año":2025,"Proyecto - Categoria":"CATEGORÍA D","Proyecto - Area":"Indagación científica (indagación de tipo descriptiva y experimental)","Estudiante - Genero":"Femenino","Cant_Estudiantes":62,"Porcentaje":64.6},{"Año":2025,"Proyecto - Categoria":"CATEGORÍA D","Proyecto - Area":"Indagación científica (indagación de tipo descriptiva y experimental)","Estudiante - Genero":"Masculino","Cant_Estudiantes":34,"Porcentaje":35.4},{"Año":2025,"Proyecto - Categoria":"CATEGORÍA D","Proyecto - Area":"Soluciones tecnológicas","Estudiante - Genero":"Femenino","Cant_Estudiantes":71,"Porcentaje":57.7},{"Año":2025,"Proyecto - Categoria":"CATEGORÍA D","Proyecto - Area":"Soluciones tecnológicas","Estudiante - Genero":"Masculino","Cant_Estudiantes":52,"Porcentaje":42.3},{"Año":2025,"Proyecto - Categoria":"CATEGORÍA E","Proyecto - Area":"Ciencias Sociales","Estudiante - Genero":"Femenino","Cant_Estudiantes":38,"Porcentaje":70.4},{"Año":2025,"Proyecto - Categoria":"CATEGORÍA E","Proyecto - Area":"Ciencias Sociales","Estudiante - Genero":"Masculino","Cant_Estudiantes":16,"Porcentaje":29.6},{"Año":2025,"Proyecto - Categoria":"CATEGORÍA E","Proyecto - Area":"Indagación científica (indagación de tipo descriptiva y experimental)","Estudiante - Genero":"Femenino","Cant_Estudiantes":95,"Porcentaje":68.3},{"Año":2025,"Proyecto - Categoria":"CATEGORÍA E","Proyecto - Area":"Indagación científica (indagación de tipo descriptiva y experimental)","Estudiante - Genero":"Masculino","Cant_Estudiantes":44,"Porcentaje":31.7},{"Año":2025,"Proyecto - Categoria":"CATEGORÍA E","Proyecto - Area":"Soluciones tecnológicas","Estudiante - Genero":"Femenino","Cant_Estudiantes":102,"Porcentaje":57.6},{"Año":2025,"Proyecto - Categoria":"CATEGORÍA E","Proyecto - Area":"Soluciones tecnológicas","Estudiante - Genero":"Masculino","Cant_Estudiantes":75,"Porcentaje":42.4}]