[{"IE - Provincia":"CANDARAVE","IE - Distrito":"CAIRANI","IE - Gestion":"Privada","Participantes_Eureka":0,"Año":2018,"Total_Escale":1,"Porcentaje (%)":0.0},{"IE - Provincia":"CANDARAVE","IE - Distrito":"QUILAHUANI","IE - Gestion":"Privada","Participantes_Eureka":0,"Año":2018,"Total_Escale":2,"Porcentaje (%)":0.0},{"IE - Provincia":"JORGE BASADRE","IE - Distrito":"ILABAYA","IE - Gestion":"Privada","Participantes_Eureka":1,"Año":2018,"Total_Escale":5,"Porcentaje (%)":20.0},{"IE - Provincia":"JORGE BASADRE","IE - Distrito":"ITE","IE - Gestion":"Privada","Participantes_Eureka":0,"Año":2018,"Total_Escale":1,"Porcentaje (%)":0.0},{"IE - Provincia":"TACNA","IE - Distrito":"ALTO DE LA ALIANZA","IE - Gestion":"Privada","Participantes_Eureka":0,"Año":2018,"Total_Escale":2,"Porcentaje (%)":0.0},{"IE - Provincia":"TACNA","IE - Distrito":"CIUDAD NUEVA","IE - Gestion":"Privada","Participantes_Eureka":0,"Año":2018,"Total_Escale":1,"Porcentaje (%)":0.0},{"IE - Provincia":"TACNA","IE - Distrito":"CORONEL GREGORIO ALBARRACIN LANCHIPA","IE - Gestion":"Privada","Participantes_Eureka":2,"Año":2018,"Total_Escale":14,"Porcentaje (%)":14.3},{"IE - Provincia":"TACNA","IE - Distrito":"POCOLLAY","IE - Gestion":"Privada","Participantes_Eureka":0,"Año":2018,"Total_Escale":7,"Porcentaje (%)":0.0},{"IE - Provincia":"TACNA","IE - Distrito":"TACNA","IE - Gestion":"Privada","Participantes_Eureka":10,"Año":2018,"Total_Escale":66,"Porcentaje (%)":15.2},{"IE - Provincia":"CANDARAVE","IE - Distrito":"CAIRANI","IE - Gestion":"Privada","Participantes_Eureka":0,"Año":2019,"Total_Escale":1,"Porcentaje (%)":0.0},{"IE - Provincia":"CANDARAVE","IE - Distrito":"QUILAHUANI","IE - Gestion":"Privada","Participantes_Eureka":0,"Año":2019,"Total_Escale":2,"Porcentaje (%)":0.0},{"IE - Provincia":"JORGE BASADRE","IE - Distrito":"ILABAYA","IE - Gestion":"Privada","Participantes_Eureka":2,"Año":2019,"Total_Escale":5,"Porcentaje (%)":40.0},{"IE - Provincia":"JORGE BASADRE","IE - Distrito":"ITE","IE - Gestion":"Privada","Participantes_Eureka":0,"Año":2019,"Total_Escale":1,"Porcentaje (%)":0.0},{"IE - Provincia":"TACNA","IE - Distrito":"ALTO DE LA ALIANZA","IE - Gestion":"Privada","Participantes_Eureka":0,"Año":2019,"Total_Escale":2,"Porcentaje (%)":0.0},{"IE - Provincia":"TACNA","IE - Distrito":"CIUDAD NUEVA","IE - Gestion":"Privada","Participantes_Eureka":0,"Año":2019,"Total_Escale":1,"Porcentaje (%)":0.0},{"IE - Provincia":"TACNA","IE - Distrito":"CORONEL GREGORIO ALBARRACIN LANCHIPA","IE - Gestion":"Privada","Participantes_Eureka":2,"Año":2019,"Total_Escale":14,"Porcentaje (%)":14.3},{"IE - Provincia":"TACNA","IE - Distrito":"POCOLLAY","IE - Gestion":"Privada","Participantes_Eureka":0,"Año":2019,"Total_Escale":7,"Porcentaje (%)":0.0},{"IE - Provincia":"TACNA","IE - Distrito":"TACNA","IE - Gestion":"Privada","Participantes_Eureka":14,"Año":2019,"Total_Escale":67,"Porcentaje (%)":20.9},{"IE - Provincia":"CANDARAVE","IE - Distrito":"CAIRANI","IE - Gestion":"Privada","Participantes_Eureka":0,"Año":2021,"Total_Escale":1,"Porcentaje (%)":0.0},{"IE - Provincia":"CANDARAVE","IE - Distrito":"QUILAHUANI","IE - Gestion":"Privada","Participantes_Eureka":0,"Año":2021,"Total_Escale":2,"Porcentaje (%)":0.0},{"IE - Provincia":"JORGE BASADRE","IE - Distrito":"ILABAYA","IE - Gestion":"Privada","Participantes_Eureka":2,"Año":2021,"Total_Escale":5,"Porcentaje (%)":40.0},{"IE - Provincia":"JORGE BASADRE","IE - Distrito":"ITE","IE - Gestion":"Privada","Participantes_Eureka":0,"Año":2021,"Total_Escale":1,"Porcentaje (%)":0.0},{"IE - Provincia":"TACNA","IE - Distrito":"ALTO DE LA ALIANZA","IE - Gestion":"Privada","Participantes_Eureka":0,"Año":2021,"Total_Escale":2,"Porcentaje (%)":0.0},{"IE - Provincia":"TACNA","IE - Distrito":"CIUDAD NUEVA","IE - Gestion":"Privada","Participantes_Eureka":0,"Año":2021,"Total_Escale":1,"Porcentaje (%)":0.0},{"IE - Provincia":"TACNA","IE - Distrito":"CORONEL GREGORIO ALBARRACIN LANCHIPA","IE - Gestion":"Privada","Participantes_Eureka":1,"Año":2021,"Total_Escale":15,"Porcentaje (%)":6.7},{"IE - Provincia":"TACNA","IE - Distrito":"POCOLLAY","IE - Gestion":"Privada","Participantes_Eureka":0,"Año":2021,"Total_Escale":9,"Porcentaje (%)":0.0},{"IE - Provincia":"TACNA","IE - Distrito":"TACNA","IE - Gestion":"Privada","Participantes_Eureka":6,"Año":2021,"Total_Escale":68,"Porcentaje (%)":8.8},{"IE - Provincia":"CANDARAVE","IE - Distrito":"CAIRANI","IE - Gestion":"Privada","Participantes_Eureka":0,"Año":2022,"Total_Escale":1,"Porcentaje (%)":0.0},{"IE - Provincia":"CANDARAVE","IE - Distrito":"QUILAHUANI","IE - Gestion":"Privada","Participantes_Eureka":0,"Año":2022,"Total_Escale":2,"Porcentaje (%)":0.0},{"IE - Provincia":"JORGE BASADRE","IE - Distrito":"ILABAYA","IE - Gestion":"Privada","Participantes_Eureka":2,"Año":2022,"Total_Escale":5,"Porcentaje (%)":40.0},{"IE - Provincia":"JORGE BASADRE","IE - Distrito":"ITE","IE - Gestion":"Privada","Participantes_Eureka":0,"Año":2022,"Total_Escale":1,"Porcentaje (%)":0.0},{"IE - Provincia":"TACNA","IE - Distrito":"ALTO DE LA ALIANZA","IE - Gestion":"Privada","Participantes_Eureka":0,"Año":2022,"Total_Escale":2,"Porcentaje (%)":0.0},{"IE - Provincia":"TACNA","IE - Distrito":"CIUDAD NUEVA","IE - Gestion":"Privada","Participantes_Eureka":0,"Año":2022,"Total_Escale":1,"Porcentaje (%)":0.0},{"IE - Provincia":"TACNA","IE - Distrito":"CORONEL GREGORIO ALBARRACIN LANCHIPA","IE - Gestion":"Privada","Participantes_Eureka":1,"Año":2022,"Total_Escale":15,"Porcentaje (%)":6.7},{"IE - Provincia":"TACNA","IE - Distrito":"POCOLLAY","IE - Gestion":"Privada","Participantes_Eureka":0,"Año":2022,"Total_Escale":10,"Porcentaje (%)":0.0},{"IE - Provincia":"TACNA","IE - Distrito":"TACNA","IE - Gestion":"Privada","Participantes_Eureka":4,"Año":2022,"Total_Escale":68,"Porcentaje (%)":5.9},{"IE - Provincia":"CANDARAVE","IE - Distrito":"CAIRANI","IE - Gestion":"Privada","Participantes_Eureka":0,"Año":2023,"Total_Escale":1,"Porcentaje (%)":0.0},{"IE - Provincia":"CANDARAVE","IE - Distrito":"QUILAHUANI","IE - Gestion":"Privada","Participantes_Eureka":0,"Año":2023,"Total_Escale":2,"Porcentaje (%)":0.0},{"IE - Provincia":"JORGE BASADRE","IE - Distrito":"ILABAYA","IE - Gestion":"Privada","Participantes_Eureka":2,"Año":2023,"Total_Escale":5,"Porcentaje (%)":40.0},{"IE - Provincia":"JORGE BASADRE","IE - Distrito":"ITE","IE - Gestion":"Privada","Participantes_Eureka":0,"Año":2023,"Total_Escale":1,"Porcentaje (%)":0.0},{"IE - Provincia":"TACNA","IE - Distrito":"ALTO DE LA ALIANZA","IE - Gestion":"Privada","Participantes_Eureka":0,"Año":2023,"Total_Escale":2,"Porcentaje (%)":0.0},{"IE - Provincia":"TACNA","IE - Distrito":"CIUDAD NUEVA","IE - Gestion":"Privada","Participantes_Eureka":0,"Año":2023,"Total_Escale":1,"Porcentaje (%)":0.0},{"IE - Provincia":"TACNA","IE - Distrito":"CORONEL GREGORIO ALBARRACIN LANCHIPA","IE - Gestion":"Privada","Participantes_Eureka":1,"Año":2023,"Total_Escale":15,"Porcentaje (%)":6.7},{"IE - Provincia":"TACNA","IE - Distrito":"POCOLLAY","IE - Gestion":"Privada","Participantes_Eureka":1,"Año":2023,"Total_Escale":10,"Porcentaje (%)":10.0},{"IE - Provincia":"TACNA","IE - Distrito":"TACNA","IE - Gestion":"Privada","Participantes_Eureka":9,"Año":2023,"Total_Escale":69,"Porcentaje (%)":13.0},{"IE - Provincia":"CANDARAVE","IE - Distrito":"CAIRANI","IE - Gestion":"Privada","Participantes_Eureka":0,"Año":2024,"Total_Escale":1,"Porcentaje (%)":0.0},{"IE - Provincia":"CANDARAVE","IE - Distrito":"QUILAHUANI","IE - Gestion":"Privada","Participantes_Eureka":0,"Año":2024,"Total_Escale":2,"Porcentaje (%)":0.0},{"IE - Provincia":"JORGE BASADRE","IE - Distrito":"ILABAYA","IE - Gestion":"Privada","Participantes_Eureka":2,"Año":2024,"Total_Escale":5,"Porcentaje (%)":40.0},{"IE - Provincia":"JORGE BASADRE","IE - Distrito":"ITE","IE - Gestion":"Privada","Participantes_Eureka":0,"Año":2024,"Total_Escale":1,"Porcentaje (%)":0.0},{"IE - Provincia":"TACNA","IE - Distrito":"ALTO DE LA ALIANZA","IE - Gestion":"Privada","Participantes_Eureka":0,"Año":2024,"Total_Escale":2,"Porcentaje (%)":0.0},{"IE - Provincia":"TACNA","IE - Distrito":"CIUDAD NUEVA","IE - Gestion":"Privada","Participantes_Eureka":0,"Año":2024,"Total_Escale":1,"Porcentaje (%)":0.0},{"IE - Provincia":"TACNA","IE - Distrito":"CORONEL GREGORIO ALBARRACIN LANCHIPA","IE - Gestion":"Privada","Participantes_Eureka":1,"Año":2024,"Total_Escale":15,"Porcentaje (%)":6.7},{"IE - Provincia":"TACNA","IE - Distrito":"POCOLLAY","IE - Gestion":"Privada","Participantes_Eureka":1,"Año":2024,"Total_Escale":11,"Porcentaje (%)":9.1},{"IE - Provincia":"TACNA","IE - Distrito":"TACNA","IE - Gestion":"Privada","Participantes_Eureka":15,"Año":2024,"Total_Escale":70,"Porcentaje (%)":21.4},{"IE - Provincia":"CANDARAVE","IE - Distrito":"CAIRANI","IE - Gestion":"Privada","Participantes_Eureka":0,"Año":2025,"Total_Escale":1,"Porcentaje (%)":0.0},{"IE - Provincia":"CANDARAVE","IE - Distrito":"QUILAHUANI","IE - Gestion":"Privada","Participantes_Eureka":0,"Año":2025,"Total_Escale":2,"Porcentaje (%)":0.0},{"IE - Provincia":"JORGE BASADRE","IE - Distrito":"ILABAYA","IE - Gestion":"Privada","Participantes_Eureka":2,"Año":2025,"Total_Escale":5,"Porcentaje (%)":40.0},{"IE - Provincia":"JORGE BASADRE","IE - Distrito":"ITE","IE - Gestion":"Privada","Participantes_Eureka":0,"Año":2025,"Total_Escale":1,"Porcentaje (%)":0.0},{"IE - Provincia":"TACNA","IE - Distrito":"ALTO DE LA ALIANZA","IE - Gestion":"Privada","Participantes_Eureka":0,"Año":2025,"Total_Escale":2,"Porcentaje (%)":0.0},{"IE - Provincia":"TACNA","IE - Distrito":"CIUDAD NUEVA","IE - Gestion":"Privada","Participantes_Eureka":1,"Año":2025,"Total_Escale":1,"Porcentaje (%)":100.0},{"IE - Provincia":"TACNA","IE - Distrito":"CORONEL GREGORIO ALBARRACIN LANCHIPA","IE - Gestion":"Privada","Participantes_Eureka":2,"Año":2025,"Total_Escale":15,"Porcentaje (%)":13.3},{"IE - Provincia":"TACNA","IE - Distrito":"POCOLLAY","IE - Gestion":"Privada","Participantes_Eureka":2,"Año":2025,"Total_Escale":11,"Porcentaje (%)":18.2},{"IE - Provincia":"TACNA","IE - Distrito":"TACNA","IE - Gestion":"Privada","Participantes_Eureka":16,"Año":2025,"Total_Escale":70,"Porcentaje (%)":22.9}]